zhlid/__init__.py
zhlid/model.py
zhlid-0.1.1.dist-info/METADATA
zhlid-0.1.1.dist-info/WHEEL
zhlid-0.1.1.dist-info/licenses/LICENSE
zhlid-0.1.1.dist-info/RECORD
