Metadata-Version: 2.4
Name: zhlid
Version: 0.1.1
Summary: ZHLID: Fine-grained Chinese Language Identification Package
Author-email: Lung-Chuan Chen <blaze7451@gmail.com>
License: Apache-2.0
License-File: LICENSE
Requires-Python: >=3.9
Requires-Dist: accelerate>=1.10.0
Requires-Dist: pandas>=2.3.2
Requires-Dist: torch>=2.8.0
Requires-Dist: transformers>=4.55.4
